{
	"animation": {
		"stage": { "id": "scene", "width": 1280, "height": 760, "fill": "black" },

		"cast": {
			"home": {
				"geometry": { "x": 0, "y": 0, "width": 1280, "height": 760, "fill": "black", "type": "rect" }
			},
			
			"title": {
				"geometry": { "x": 567, "y": 600, "type": "group" }
			},

			"title_text": {
				"group": "title",
				"geometry": { "x": 0, "y": 0, "text": "Semmeringbahn", "fontSize": "53", "fill": "white", "align": "center", "type": "text" }
			},



			"luftbild": {
				"geometry": { "x": 19, "y": 0, "src": "Luftbild1.jpg", "type": "image" }
			},


			"hoehenlinien": {
				"geometry": { "x": 0, "y": 0, "src": "Karte.jpg", "type": "image" }
			},


			"unesco_nahbereich": {
				"geometry": { "x": 269, "y": 29, "src": "unesco_nahbereich.png", "type": "image" }
			},

			"unesco_siedlung": {
				"geometry": { "x": 488, "y": 10, "src": "unesco_siedlung.png", "type": "image" }
			},



			"wsg_grundwasser": {
				"geometry": { "x": 19, "y":0, "src": "wsg_grundwasser.png", "type": "image" }
			},

			"wsg_quellschutz": {
				"geometry": { "x": 183, "y":119, "src": "wsg_quellschutz.png", "type": "image" }
			},

			"wsg_wirtschaft": {
				"geometry": { "x": 1192, "y":89, "src": "wsg_wirtschaft.png", "type": "image" }
			},

			"wsg_brunnenschutz": {
				"geometry": { "x": 1149, "y": 138, "src": "wsg_brunnenschutz.png", "type": "image" }
			},



			"lsg_veitsch": {
				"geometry": { "x": 19, "y":0, "src": "lsg_veitsch.png", "type": "image" }
			},

			"lsg_rax": {
				"geometry": { "x": 395, "y":0, "src": "lsg_rax.png", "type": "image" }
			},

			"lsg_natura2000": {
				"geometry": { "x": 395, "y":0, "src": "lsg_natura2000.png", "type": "image" }
			},

			"lsg_stuhleck": {
				"geometry": { "x": 234, "y":888, "src": "lsg_stuhleck.png", "type": "image" }
			},



			"txt_gloggnitz": {
				"geometry": { "x": 1100, "y": 153, "text": "Gloggnitz", "type": "text", "fill": "white", "fontSize": 20, "align": "center" }
			},

			"txt_payerbach": {
				"geometry": { "x": 833, "y": 30, "text": "Payerbach", "type": "text", "fill": "white", "fontSize": 20, "align": "center" }
			},

			"txt_krauselklause": {
				"geometry": { "x": 633, "y": 167, "text": "Krauselklause Viadukt", "type": "text", "fill": "white", "fontSize": 20, "align": "center" }
			},

			"txt_bolleroswand": {
				"geometry": { "x": 567, "y": 200, "text": "Bollerostunnel", "type": "text", "fill": "white", "fontSize": 20, "align": "center" }
			},

			"txt_kalterinne": {
				"geometry": { "x": 500, "y": 233, "text": "Kalte Rinne Viadukt", "type": "text", "fill": "white", "fontSize": 20, "align": "center" }
			},

			"txt_adlitzgraben": {
				"geometry": { "x": 520, "y": 307, "text": "Adlitzgraben Viadukt", "type": "text", "fill": "white", "fontSize": 20, "align": "center" }
			},

			"txt_semmering": {
				"geometry": { "x": 620, "y": 353, "text": "Semmering", "type": "text", "fill": "white", "fontSize": 20, "align": "center" }
			},

			"txt_muerzzuschlag": {
				"geometry": { "x": 253, "y": 500, "text": "Mürzzuschlag", "type": "text", "fill": "white", "fontSize": 20, "align": "center" }
			},





			"s00": {
				"geometry": { "x": 0, "y": 0, "src": "s00a.png", "type": "image" }
			},

			"s_semmering": {
				"geometry": { "x": 19, "y": 0, "src": "s_semmering.png", "type": "image" }
			},

			"s01": {
				"geometry": { "x": 855, "y": 53, "src": "s01_1254-79.png", "type": "image" }
			},

			"s02": {
				"geometry": { "x": 877, "y": 85, "src": "s02_1286-127.png", "type": "image" }
			},

			"s03": {
				"geometry": { "x": 942, "y": 148, "src": "s03_1384-222.png", "type": "image" }
			},

			"s04": {
				"geometry": { "x": 897, "y": 175, "src": "s04_1316-263.png", "type": "image" }
			},

			"s05": {
				"geometry": { "x": 805, "y": 203, "src": "s05_1179-304.png", "type": "image" }
			},

			"s06": {
				"geometry": { "x": 715, "y": 212, "src": "s06_1044-318.png", "type": "image" }
			},

			"s07": {
				"geometry": { "x": 691, "y": 234, "src": "s07_1007-351.png", "type": "image" }
			},

			"s08": {
				"geometry": { "x": 730, "y": 274, "src": "s08_1066-411.png", "type": "image" }
			},

			"s09": {
				"geometry": { "x": 742, "y": 307, "src": "s09_1084-460.png", "type": "image" }
			},

			"s_sued": {
				"geometry": { "x": 324, "y": 369, "src": "s_sued_457-553.png", "type": "image" }
			},

			"k_leporello": {
				"geometry": { "x": 673, "y": 38, "src": "k_leporello.jpg", "type": "image" }
			},
			
			"k_tallachini": {
				"geometry": { "x": 660, "y": 212, "src": "k_tallachini.jpg", "type": "image" }
			},
			
			"s_tallachini": {
				"geometry": { "x": 660, "y": 212, "src": "s_tallachini.png", "type": "image" }
			}
		},



		"sequence": [
			{
				"name": "main",
				"start": 0,
				"end": 1000,
				"loop": 0,

				"cast": {
					"home" : {
						"layer": "main",
						"keys": [
							{ "time": 0, "opacity": 1 }
						]
					},
					
					"luftbild" : {
						"layer": "main",
						"keys": [
							{ "time": 0, "opacity": 1 }
						]
					}
				}
			},

			{
				"name": "setup",
				"start": 0,
				"end": 0,
				"loop": 0,
				"cast": {
					"hoehenlinien": {
						"layer": "main",
						"keys": [
							{ "time": 0, "opacity": 1 }
						]
					}
				}
			},

			{
				"name": "leporello",
				"start": 0,
				"end": 625,
				"loop": 1,
				"onstop": "main",

				"event": [
					{ "time": 50, "action": "stop" },
					{ "time": 100, "action": "stop" },
					{ "time": 150, "action": "stop" },
					{ "time": 200, "action": "stop" },
					{ "time": 250, "action": "stop" },
					{ "time": 300, "action": "stop" },
					{ "time": 350, "action": "stop" },
					{ "time": 400, "action": "stop" },
					{ "time": 450, "action": "stop" },
					{ "time": 500, "action": "stop" },
					{ "time": 550, "action": "stop" },
					{ "time": 600, "action": "stop" }
				],


				"cast": {
					"luftbild" : {
						"layer": "luftbild",
						"keys": [
							{ "time": 75, "opacity": 1 },
							{ "time": 100, "opacity": 0.5 },
							{ "time": 600, "opacity": 0.5 },
							{ "time": 625, "opacity": 1 }
						]
					},

					"k_leporello" : {
						"layer": "luftbild",
						"keys": [
							{ "time": 75, "opacity": 0 },
							{ "time": 100, "opacity": 1 },
							{ "time": 600, "opacity": 1 },
							{ "time": 625, "opacity": 0 }
						]
					},

					"txt_gloggnitz" : {
						"layer": "luftbild",
						"keys": [
							{ "time": 0, "opacity": 0 },
							{ "time": 25, "opacity": 1 },
							{ "time": 75, "opacity": 1 },
							{ "time": 100, "opacity": 0.3 },
							{ "time": 600, "opacity": 0.3 },
							{ "time": 625, "opacity": 0 }
						]
					},

					"txt_payerbach" : {
						"layer": "luftbild",
						"keys": [
							{ "time": 0, "opacity": 0 },
							{ "time": 25, "opacity": 1 },
							{ "time": 600, "opacity": 1 },
							{ "time": 625, "opacity": 0 }
						]
					},

					"txt_semmering" : {
						"layer": "luftbild",
						"keys": [
							{ "time": 0, "opacity": 0 },
							{ "time": 25, "opacity": 1 },
							{ "time": 600, "opacity": 1 },
							{ "time": 625, "opacity": 0 }
						]
					},

					"txt_muerzzuschlag" : {
						"layer": "luftbild",
						"keys": [
							{ "time": 0, "opacity": 0 },
							{ "time": 25, "opacity": 1 },
							{ "time": 75, "opacity": 1 },
							{ "time": 100, "opacity": 0.3 },
							{ "time": 600, "opacity": 0.3 },
							{ "time": 625, "opacity": 0 }
						]
					},

					"s00": {
						"layer": "bahn",
						"keys": [
							{ "time": 0, "opacity": 0 },
							{ "time": 25, "opacity": 1 },
							{ "time": 75, "opacity": 1 },
							{ "time": 100, "opacity": 0.3 },
							{ "time": 600, "opacity": 0.3 },
							{ "time": 625, "opacity": 0 }
						]
					},

					"s_sued": {
						"layer": "bahn",
						"keys": [
							{ "time": 0, "opacity": 0 },
							{ "time": 25, "opacity": 1 },
							{ "time": 75, "opacity": 1 },
							{ "time": 100, "opacity": 0.3 },
							{ "time": 600, "opacity": 0.3 },
							{ "time": 625, "opacity": 0 }
						]
					},

					"s01": {
						"layer": "bahn",
						"keys": [
							{ "time": 25, "opacity": 0 },
							{ "time": 50, "opacity": 1 },
							{ "time": 75, "opacity": 0 },
							{ "time": 125, "opacity": 0 },
							{ "time": 150, "opacity": 1 },
							{ "time": 175, "opacity": 0.3 },
							{ "time": 575, "opacity": 0.3 },
							{ "time": 600, "opacity": 1 },
							{ "time": 625, "opacity": 0 }
						]
					},

					"s02": {
						"layer": "bahn",
						"keys": [
							{ "time": 0, "opacity": 0 },
							{ "time": 25, "opacity": 1 },
							{ "time": 75, "opacity": 0 },
							{ "time": 175, "opacity": 0 },
							{ "time": 200, "opacity": 1 },
							{ "time": 225, "opacity": 0.3 },
							{ "time": 575, "opacity": 0.3 },
							{ "time": 600, "opacity": 1 },
							{ "time": 625, "opacity": 0 }
						]
					},

					"s03": {
						"layer": "bahn",
						"keys": [
							{ "time": 0, "opacity": 0 },
							{ "time": 25, "opacity": 1 },
							{ "time": 75, "opacity": 0 },
							{ "time": 225, "opacity": 0 },
							{ "time": 250, "opacity": 1 },
							{ "time": 275, "opacity": 0.3 },
							{ "time": 575, "opacity": 0.3 },
							{ "time": 600, "opacity": 1 },
							{ "time": 625, "opacity": 0 }
						]
					},

					"s04": {
						"layer": "bahn",
						"keys": [
							{ "time": 0, "opacity": 0 },
							{ "time": 25, "opacity": 1 },
							{ "time": 75, "opacity": 0 },
							{ "time": 275, "opacity": 0 },
							{ "time": 300, "opacity": 1 },
							{ "time": 325, "opacity": 0.3 },
							{ "time": 575, "opacity": 0.3 },
							{ "time": 600, "opacity": 1 },
							{ "time": 625, "opacity": 0 }
						]
					},

					"s05": {
						"layer": "bahn",
						"keys": [
							{ "time": 0, "opacity": 0 },
							{ "time": 25, "opacity": 1 },
							{ "time": 75, "opacity": 0 },
							{ "time": 325, "opacity": 0 },
							{ "time": 350, "opacity": 1 },
							{ "time": 375, "opacity": 0.3 },
							{ "time": 575, "opacity": 0.3 },
							{ "time": 600, "opacity": 1 },
							{ "time": 625, "opacity": 0 }
						]
					},

					"s06": {
						"layer": "bahn",
						"keys": [
							{ "time": 0, "opacity": 0 },
							{ "time": 25, "opacity": 1 },
							{ "time": 75, "opacity": 0 },
							{ "time": 375, "opacity": 0 },
							{ "time": 400, "opacity": 1 },
							{ "time": 425, "opacity": 0.3 },
							{ "time": 575, "opacity": 0.3 },
							{ "time": 600, "opacity": 1 },
							{ "time": 625, "opacity": 0 }
						]
					},

					"s07": {
						"layer": "bahn",
						"keys": [
							{ "time": 0, "opacity": 0 },
							{ "time": 25, "opacity": 1 },
							{ "time": 75, "opacity": 0 },
							{ "time": 425, "opacity": 0 },
							{ "time": 450, "opacity": 1 },
							{ "time": 475, "opacity": 0.3 },
							{ "time": 575, "opacity": 0.3 },
							{ "time": 600, "opacity": 1 },
							{ "time": 625, "opacity": 0 }
						]
					},

					"s08": {
						"layer": "bahn",
						"keys": [
							{ "time": 0, "opacity": 0 },
							{ "time": 25, "opacity": 1 },
							{ "time": 75, "opacity": 0 },
							{ "time": 475, "opacity": 0 },
							{ "time": 500, "opacity": 1 },
							{ "time": 525, "opacity": 0.3 },
							{ "time": 575, "opacity": 0.3 },
							{ "time": 600, "opacity": 1 },
							{ "time": 625, "opacity": 0 }
						]
					},

					"s09": {
						"layer": "bahn",
						"keys": [
							{ "time": 0, "opacity": 0 },
							{ "time": 25, "opacity": 1 },
							{ "time": 75, "opacity": 0 },
							{ "time": 525, "opacity": 0 },
							{ "time": 550, "opacity": 1 },
							{ "time": 600, "opacity": 1 },
							{ "time": 625, "opacity": 0 }
						]
					}
				}
			},


			{
				"name": "benkert",
				"start": 0,
				"end": 725,
				"loop": 1,
				"onstop": "main",

				"event": [
					{ "time": 50, "action": "stop" },
					{ "time": 100, "action": "stop" },
					{ "time": 150, "action": "stop" },
					{ "time": 200, "action": "stop" },
					{ "time": 250, "action": "stop" },
					{ "time": 300, "action": "stop" },
					{ "time": 350, "action": "stop" },
					{ "time": 400, "action": "stop" },
					{ "time": 450, "action": "stop" },
					{ "time": 500, "action": "stop" },
					{ "time": 550, "action": "stop" },
					{ "time": 600, "action": "stop" },
					{ "time": 650, "action": "stop" },
					{ "time": 700, "action": "stop" }
				],


				"cast": {
					"luftbild" : {
						"layer": "luftbild",
						"keys": [
							{ "time": 75, "opacity": 1 },
							{ "time": 100, "opacity": 0.5 },
							{ "time": 700, "opacity": 0.5 },
							{ "time": 725, "opacity": 1 }
						]
					},

					"txt_gloggnitz" : {
						"layer": "luftbild",
						"keys": [
							{ "time": 25, "opacity": 0 },
							{ "time": 50, "opacity": 1 },
							{ "time": 75, "opacity": 1 },
							{ "time": 100, "opacity": 0.3 },
							{ "time": 700, "opacity": 0.3 },
							{ "time": 725, "opacity": 0 }
						]
					},

					"txt_payerbach" : {
						"layer": "luftbild",
						"keys": [
							{ "time": 25, "opacity": 0 },
							{ "time": 50, "opacity": 1 },
							{ "time": 75, "opacity": 1 },
							{ "time": 100, "opacity": 0.3 },
							{ "time": 700, "opacity": 0.3 },
							{ "time": 725, "opacity": 0 }
						]
					},

					"txt_semmering" : {
						"layer": "luftbild",
						"keys": [
							{ "time": 25, "opacity": 0 },
							{ "time": 50, "opacity": 1 },
							{ "time": 75, "opacity": 1 },
							{ "time": 100, "opacity": 0.3 },
							{ "time": 700, "opacity": 0.3 },
							{ "time": 725, "opacity": 0 }
						]
					},

					"txt_muerzzuschlag" : {
						"layer": "luftbild",
						"keys": [
							{ "time": 25, "opacity": 0 },
							{ "time": 50, "opacity": 1 },
							{ "time": 75, "opacity": 1 },
							{ "time": 100, "opacity": 0.3 },
							{ "time": 700, "opacity": 0.3 },
							{ "time": 725, "opacity": 0 }
						]
					},

					"s00" : {
						"layer": "luftbild",
						"keys": [
							{ "time": 25, "opacity": 0 },
							{ "time": 50, "opacity": 1 },
							{ "time": 75, "opacity": 1 },
							{ "time": 100, "opacity": 0.3 },
							{ "time": 700, "opacity": 0.3 },
							{ "time": 725, "opacity": 0 }
						]
					},

					"s_semmering" : {
						"layer": "luftbild",
						"keys": [
							{ "time": 25, "opacity": 0 },
							{ "time": 50, "opacity": 1 },
							{ "time": 75, "opacity": 1 },
							{ "time": 100, "opacity": 0.3 },
							{ "time": 700, "opacity": 0.3 },
							{ "time": 725, "opacity": 0 }
						]
					},

					"k_tallachini" : {
						"layer": "luftbild",
						"keys": [
							{ "time": 75, "opacity": 0 },
							{ "time": 100, "opacity": 1 },
							{ "time": 700, "opacity": 1 },
							{ "time": 725, "opacity": 0 }
						]
					},
					
					"s_tallachini" : {
						"layer": "luftbild",
						"keys": [
							{ "time": 75, "opacity": 0 },
							{ "time": 100, "opacity": 1 },
							{ "time": 700, "opacity": 1 },
							{ "time": 725, "opacity": 0 }
						]
					},

					"txt_krauselklause" : {
						"layer": "luftbild",
						"keys": [
							{ "time": 125, "opacity": 0 },
							{ "time": 150, "opacity": 1 },
							{ "time": 200, "opacity": 1 },
							{ "time": 225, "opacity": 0 }
						]
					},
					
					"txt_bolleroswand" : {
						"layer": "luftbild",
						"keys": [
							{ "time": 225, "opacity": 0 },
							{ "time": 250, "opacity": 1 },
							{ "time": 275, "opacity": 0 }
						]
					},
					
					"txt_kalterinne" : {
						"layer": "luftbild",
						"keys": [
							{ "time": 275, "opacity": 0 },
							{ "time": 300, "opacity": 1 },
							{ "time": 600, "opacity": 1 },
							{ "time": 625, "opacity": 0 }
						]
					},
					
					"txt_adlitzgraben" : {
						"layer": "luftbild",
						"keys": [
							{ "time": 625, "opacity": 0 },
							{ "time": 650, "opacity": 1 },
							{ "time": 675, "opacity": 0 }
						]
					}
				}
			}

		]
	}
}
